stlite_sandbox/__init__.py
stlite_sandbox/frontend/index.html
stlite_sandbox/frontend/main.js
stlite_sandbox/frontend/streamlit-component-lib.js
stlite_sandbox/frontend/style.css
stlite_sandbox-0.2.1.dist-info/LICENSE
stlite_sandbox-0.2.1.dist-info/METADATA
stlite_sandbox-0.2.1.dist-info/WHEEL
stlite_sandbox-0.2.1.dist-info/top_level.txt
stlite_sandbox-0.2.1.dist-info/RECORD
