Metadata-Version: 2.1
Name: stlite-sandbox
Version: 0.2.1
Summary: Streamlit component that allows you add an stlite sandbox into your streamlit app. Comes with a built-in editor to allow you to change the code and see what happens.
Author: Zachary Blackwood
Author-email: zachary@streamlit.io
Requires-Python: >=3.7
License-File: LICENSE
Requires-Dist: streamlit >=1.2
Requires-Dist: jinja2
Requires-Dist: streamlit-monaco
